CODEOWNERS
LICENSE
MANIFEST.in
README.md
setup.cfg
setup.py
phaedo/__init__.py
phaedo/validators.py
phaedo.egg-info/PKG-INFO
phaedo.egg-info/SOURCES.txt
phaedo.egg-info/dependency_links.txt
phaedo.egg-info/top_level.txt
phaedo/core/__init__.py
phaedo/core/_meta.py
phaedo/core/_registry.py
phaedo/core/fields.py
phaedo/core/model.py
phaedo/core/validation/__init__.py
phaedo/core/validation/validation.py