Metadata-Version: 2.1
Name: phaedo
Version: 0.1.0
Summary: phaedo: Python domain model library for DDD (Domain Driven Development)
Home-page: https://github.com/utamaru-hiro/phaedo
Author: hiro utamaru
Author-email: lemon.flavor.jam@gmail.com
License: UNKNOWN
Platform: UNKNOWN
License-File: LICENSE
